stitcher/__init__.py
stitcher/util.py
stitcher/join.py
stitcher/canvas.py
stitcher/composition.py
stitcher/__main__.py
stitcher/tests/test_util.py
stitcher/tests/__init__.py
stitcher/profiles/lg.py
stitcher/profiles/__init__.py
stitcher/profiles/apple.py
stitcher/profiles/profile.py
stitcher/profiles/nokia.py
stitcher-1.0.0.dist-info/DESCRIPTION.rst
stitcher-1.0.0.dist-info/METADATA
stitcher-1.0.0.dist-info/metadata.json
stitcher-1.0.0.dist-info/entry_points.txt
stitcher-1.0.0.dist-info/top_level.txt
stitcher-1.0.0.dist-info/zip-safe
stitcher-1.0.0.dist-info/WHEEL
stitcher-1.0.0.dist-info/RECORD
